fenautils/__init__.py
fenautils-1.1.0.dist-info/METADATA
fenautils-1.1.0.dist-info/RECORD
fenautils-1.1.0.dist-info/WHEEL
fenautils-1.1.0.dist-info/top_level.txt
